{
   "collections": [
      {
         "collectionId": "0x5af0d9827e0c53e4799bb226655a1de152a425a5",
         "name": "Milady Maker",
         "slug": "milady",
         "contract": "0x5af0d9827e0c53e4799bb226655a1de152a425a5",
         "image": "https://i.seadn.io/gae/a_frplnavZA9g4vN3SexO5rrtaBX_cBTaJYcgrPtwQIqPhzgzUendQxiwUdr51CGPE2QyPEa1DHnkW1wLrHAv5DgfC3BP-CWpFq6BA?w=500&auto=format",
         "allTimeVolume": 33643.72707,
         "floorAskPrice": {
            "currency": {
               "contract": "0x0000000000000000000000000000000000000000",
               "name": "Ether",
               "symbol": "ETH",
               "decimals": 18
            },
            "amount": {
               "raw": "2770000000000000000",
               "decimal": 2.77,
               "usd": 5173.22243,
               "native": 2.77
            }
         },
         "openseaVerificationStatus": "verified"
      },
      {
         "collectionId": "0x2fc722c1c77170a61f17962cc4d039692f033b43",
         "name": "milady aura",
         "slug": "miladyaura",
         "contract": "0x2fc722c1c77170a61f17962cc4d039692f033b43",
         "image": "https://i.seadn.io/gae/RcCll0PWAnUGr1oYk250Mm0fAW5u0-pkEzOaxSHm6qiHotaqjVtePqkf0CD6v2ef1uxhrqW6KZI3ZYqfURKSiecnSd2ofngQNepxbw?w=500&auto=format",
         "allTimeVolume": 214.02947,
         "floorAskPrice": {
            "currency": {
               "contract": "0x0000000000000000000000000000000000000000",
               "name": "Ether",
               "symbol": "ETH",
               "decimals": 18
            },
            "amount": {
               "raw": "99900000000000000",
               "decimal": 0.0999,
               "usd": 186.57217,
               "native": 0.0999
            }
         },
         "openseaVerificationStatus": "not_requested"
      },
      {
         "collectionId": "0x8a45fb65311ac8434aad5b8a93d1eba6ac4e813b",
         "name": "Milady, That B.I.T.C.H.",
         "slug": "miladybitch",
         "contract": "0x8a45fb65311ac8434aad5b8a93d1eba6ac4e813b",
         "image": "https://i.seadn.io/gae/Tw2F8D4nHQwVzaSZfk3T22na23rf1K0KW9lPRbnnx6--SyzCaL7tsAZcRBujBPGI6z_GT89ZH59g-GHjAfr_uRK2XvJUWCDggTIX8Q?w=500&auto=format",
         "allTimeVolume": 177.0703,
         "floorAskPrice": {
            "currency": {
               "contract": "0x0000000000000000000000000000000000000000",
               "name": "Ether",
               "symbol": "ETH",
               "decimals": 18
            },
            "amount": {
               "raw": "1000000000000000000",
               "decimal": 1,
               "usd": 1867.58932,
               "native": 1
            }
         },
         "openseaVerificationStatus": "requested"
      },
      {
         "collectionId": "0xafe12842e3703a3cc3a71d9463389b1bf2c5bc1c",
         "name": "Bored Milady Maker",
         "slug": "boredmilady",
         "contract": "0xafe12842e3703a3cc3a71d9463389b1bf2c5bc1c",
         "image": "https://i.seadn.io/gcs/files/48ffae0463ccbd2c0dcf0cce4a457a99.png?w=500&auto=format",
         "allTimeVolume": 150.14017,
         "floorAskPrice": {
            "currency": {
               "contract": "0x0000000000000000000000000000000000000000",
               "name": "Ether",
               "symbol": "ETH",
               "decimals": 18
            },
            "amount": {
               "raw": "7999999999999997",
               "decimal": 0.008,
               "usd": 14.94071,
               "native": 0.008
            }
         },
         "openseaVerificationStatus": "not_requested"
      },
      {
         "collectionId": "0x94fe1d5de3a4208c7411ae21968e044abc17be48",
         "name": "Streets of Milady",
         "slug": "streetsofmilady",
         "contract": "0x94fe1d5de3a4208c7411ae21968e044abc17be48",
         "image": "https://i.seadn.io/gcs/files/407277dd45c021a2c51d204f2237360d.png?w=500&auto=format",
         "allTimeVolume": 16.9312,
         "floorAskPrice": {
            "currency": {
               "contract": "0x0000000000000000000000000000000000000000",
               "name": "Ether",
               "symbol": "ETH",
               "decimals": 18
            },
            "amount": {
               "raw": "8000000000000000",
               "decimal": 0.008,
               "usd": 14.94071,
               "native": 0.008
            }
         },
         "openseaVerificationStatus": "approved"
      },
      {
         "collectionId": "0xc62e3fd5b02618f90dd07d1e478963038fa9089c",
         "name": "milady aura petz",
         "slug": "milady-aura-petz",
         "contract": "0xc62e3fd5b02618f90dd07d1e478963038fa9089c",
         "image": "https://i.seadn.io/gcs/files/701d80b9a3c4fa2055d5c5a3a35ceb22.png?w=500&auto=format",
         "allTimeVolume": 13.55494,
         "floorAskPrice": {
            "currency": {
               "contract": "0x0000000000000000000000000000000000000000",
               "name": "Ether",
               "symbol": "ETH",
               "decimals": 18
            },
            "amount": {
               "raw": "11000000000000000",
               "decimal": 0.011,
               "usd": 20.54348,
               "native": 0.011
            }
         },
         "openseaVerificationStatus": "not_requested"
      },
      {
         "collectionId": "0x99c8a1774b1caa0e71df50b79d00be2e22f9d69a",
         "name": "RR/MILADY",
         "slug": "rr-milady",
         "contract": "0x99c8a1774b1caa0e71df50b79d00be2e22f9d69a",
         "image": "https://i.seadn.io/gcs/files/ffadb3bd3bd4225709ec5915b53d18d8.png?w=500&auto=format",
         "allTimeVolume": 8.21064,
         "floorAskPrice": {
            "currency": {
               "contract": "0x0000000000000000000000000000000000000000",
               "name": "Ether",
               "symbol": "ETH",
               "decimals": 18
            },
            "amount": {
               "raw": "9000000000000000",
               "decimal": 0.009,
               "usd": 16.8083,
               "native": 0.009
            }
         },
         "openseaVerificationStatus": "not_requested"
      },
      {
         "collectionId": "0xa5f1fc0501e7737e2f48bee930b77cd86940a293",
         "name": "NotOkayMiladys",
         "slug": "notokaymiladys",
         "contract": "0xa5f1fc0501e7737e2f48bee930b77cd86940a293",
         "image": "https://i.seadn.io/gae/VcyirAPPmOWAU5Y-BKLNAaiUEspHfSkdkm5R_ZMcLCPgZhOC_8yHnFuIEkXoJPGtGoh_oIEcBIslBX5fNMfcfj64k9tbN7bMtnnanw?w=500&auto=format",
         "allTimeVolume": 7.5086,
         "floorAskPrice": {
            "currency": {
               "contract": "0x0000000000000000000000000000000000000000",
               "name": "Ether",
               "symbol": "ETH",
               "decimals": 18
            },
            "amount": {
               "raw": "1999999999999999",
               "decimal": 0.002,
               "usd": 3.73518,
               "native": 0.002
            }
         },
         "openseaVerificationStatus": "not_requested"
      },
      {
         "collectionId": "0x880a965fae95f72fe3a3c8e87ed2c9478c8e0a29",
         "name": "MiladyRave",
         "slug": "miladyrave",
         "contract": "0x880a965fae95f72fe3a3c8e87ed2c9478c8e0a29",
         "image": "https://i.seadn.io/gcs/files/37d64cd13544707cb8d0a42830a69733.jpg?w=500&auto=format",
         "allTimeVolume": 4.47191,
         "floorAskPrice": {
            "currency": {
               "contract": "0x0000000000000000000000000000000000000000",
               "name": "Ether",
               "symbol": "ETH",
               "decimals": 18
            },
            "amount": {
               "raw": "3000000000000000",
               "decimal": 0.003,
               "usd": 5.60277,
               "native": 0.003
            }
         },
         "openseaVerificationStatus": "not_requested"
      },
      {
         "collectionId": "0x3cb9c3f0ad5ac856f277427dfcc9f3757f9bb08e",
         "name": "Timeline Game: Apes vs Miladys Trading Cards",
         "slug": "tlgame",
         "contract": "0x3cb9c3f0ad5ac856f277427dfcc9f3757f9bb08e",
         "image": "https://i.seadn.io/gcs/files/23069e0f3b1284f33551ceb22f2f613c.png?w=500&auto=format",
         "allTimeVolume": 3.75822,
         "floorAskPrice": {
            "currency": {
               "contract": "0x0000000000000000000000000000000000000000",
               "name": "Ether",
               "symbol": "ETH",
               "decimals": 18
            },
            "amount": {
               "raw": "6000000000000000",
               "decimal": 0.006,
               "usd": 11.20553,
               "native": 0.006
            }
         },
         "openseaVerificationStatus": "not_requested"
      },
      {
         "collectionId": "0xb24bab1732d34cad0a7c7035c3539aec553bf3a0",
         "name": "MiladyStation",
         "slug": "miladystation",
         "contract": "0xb24bab1732d34cad0a7c7035c3539aec553bf3a0",
         "image": "https://i.seadn.io/gcs/files/525afa6ef5bec1dfdc8d0c962c10cb65.png?w=500&auto=format",
         "allTimeVolume": 3.72351,
         "floorAskPrice": {
            "currency": {
               "contract": "0x0000000000000000000000000000000000000000",
               "name": "Ether",
               "symbol": "ETH",
               "decimals": 18
            },
            "amount": {
               "raw": "20491042826216332",
               "decimal": 0.02049,
               "usd": 38.26885,
               "native": 0.02049
            }
         },
         "openseaVerificationStatus": "not_requested"
      },
      {
         "collectionId": "0x4246200d62072cf8836f1062a115927555b9c497",
         "name": "Matrix Milady",
         "slug": "matrix-milady",
         "contract": "0x4246200d62072cf8836f1062a115927555b9c497",
         "image": "https://i.seadn.io/gcs/files/fb0913984a937b6e62999bea416a1fac.jpg?w=500&auto=format",
         "allTimeVolume": 2.13017,
         "floorAskPrice": {
            "currency": {
               "contract": "0x0000000000000000000000000000000000000000",
               "name": "Ether",
               "symbol": "ETH",
               "decimals": 18
            },
            "amount": {
               "raw": "13000000000000000",
               "decimal": 0.013,
               "usd": 24.27866,
               "native": 0.013
            }
         },
         "openseaVerificationStatus": "not_requested"
      },
      {
         "collectionId": "0xe6ec7dd8a31ae3efdf9e8c774d73053b0ee42cea",
         "name": "Milady Maker X LITE",
         "slug": "milady-maker-x-lite",
         "contract": "0xe6ec7dd8a31ae3efdf9e8c774d73053b0ee42cea",
         "image": "https://i.seadn.io/gcs/files/9c720e357d495a7d23ee5f53c717c89d.jpg?w=500&auto=format",
         "allTimeVolume": 1.58277,
         "floorAskPrice": {
            "currency": {
               "contract": "0x0000000000000000000000000000000000000000",
               "name": "Ether",
               "symbol": "ETH",
               "decimals": 18
            },
            "amount": {
               "raw": "20000000000000000",
               "decimal": 0.02,
               "usd": 37.35179,
               "native": 0.02
            }
         },
         "openseaVerificationStatus": "not_requested"
      },
      {
         "collectionId": "0x5f8e089e6f9919556f4fb43a92e80f4dc62ce107",
         "name": "Squiggle Miladys",
         "slug": "squiggle-miladys",
         "contract": "0x5f8e089e6f9919556f4fb43a92e80f4dc62ce107",
         "image": "https://i.seadn.io/gcs/files/acfff341c0866093b931edfc9e88a6a2.png?w=500&auto=format",
         "allTimeVolume": 1.144,
         "floorAskPrice": {
            "currency": {
               "contract": "0x0000000000000000000000000000000000000000",
               "name": "Ether",
               "symbol": "ETH",
               "decimals": 18
            },
            "amount": {
               "raw": "119900000000000000",
               "decimal": 0.1199,
               "usd": 223.92396,
               "native": 0.1199
            }
         },
         "openseaVerificationStatus": "not_requested"
      },
      {
         "collectionId": "0x07e8d4a25d36d7259879337a923170453944614f",
         "name": "milady mfers",
         "slug": "milady-mfers",
         "contract": "0x07e8d4a25d36d7259879337a923170453944614f",
         "image": "https://i.seadn.io/gae/b8Hs5G7__uMMDsHzDOuHTjMsovh7OmhgCQwVhqd-TZFNFBVKqUvFRwwFVLLhEwYVfFJ1fzDiBXfMgsQqrYFz7xwa-uS-WAnbTcTWOw?w=500&auto=format",
         "allTimeVolume": 0.78288,
         "floorAskPrice": {
            "currency": {
               "contract": "0x0000000000000000000000000000000000000000",
               "name": "Ether",
               "symbol": "ETH",
               "decimals": 18
            },
            "amount": {
               "raw": "10000000000000000",
               "decimal": 0.01,
               "usd": 18.67589,
               "native": 0.01
            }
         },
         "openseaVerificationStatus": "not_requested"
      },
      {
         "collectionId": "0x4a519d24a9d03e51e6da5732b16420b68943bc32",
         "name": "Azuki Milady",
         "slug": "azuki-milady",
         "contract": "0x4a519d24a9d03e51e6da5732b16420b68943bc32",
         "image": "https://i.seadn.io/gae/09yB2H_DNlvfIIANTW3aPCjrfUxbjQpgP32nZDOwDbyKIisHBjvpkDuhr_jg-ZivAspzIBAhJF85TP5rTvduZ_AaO9bCs5h2npwmcWE?w=500&auto=format",
         "allTimeVolume": 0.7633,
         "floorAskPrice": {
            "currency": {
               "contract": "0x0000000000000000000000000000000000000000",
               "name": "Ether",
               "symbol": "ETH",
               "decimals": 18
            },
            "amount": {
               "raw": "30000000000000000",
               "decimal": 0.03,
               "usd": 56.02768,
               "native": 0.03
            }
         },
         "openseaVerificationStatus": "not_requested"
      },
      {
         "collectionId": "0xc8212c46a38a688275d3da30a2319675f6c92b81",
         "name": "Hook Covered Call Instrument (Milady Maker)",
         "slug": "milady-maker-covered-calls",
         "contract": "0xc8212c46a38a688275d3da30a2319675f6c92b81",
         "image": "https://i.seadn.io/gcs/files/854fc540031c59b3bc21bb25c64368c3.png?w=500&auto=format",
         "allTimeVolume": 0.76056,
         "openseaVerificationStatus": "not_requested"
      },
      {
         "collectionId": "0xe03480e9196003d9b4106c56595a1429f7d00f87",
         "name": "Original MiladyStation",
         "slug": "miladystationclassic",
         "contract": "0xe03480e9196003d9b4106c56595a1429f7d00f87",
         "image": "https://i.seadn.io/gcs/files/bc67937697a75eeb3828de8cd24e3412.png?w=500&auto=format",
         "allTimeVolume": 0.404,
         "floorAskPrice": {
            "currency": {
               "contract": "0x0000000000000000000000000000000000000000",
               "name": "Ether",
               "symbol": "ETH",
               "decimals": 18
            },
            "amount": {
               "raw": "10000000000000000",
               "decimal": 0.01,
               "usd": 18.67589,
               "native": 0.01
            }
         },
         "openseaVerificationStatus": "not_requested"
      },
      {
         "collectionId": "0x57282f0053c25e47710e511ba7bfa0739444b543",
         "name": "Milady Christmas",
         "slug": "milady-christmas",
         "contract": "0x57282f0053c25e47710e511ba7bfa0739444b543",
         "image": "https://i.seadn.io/gcs/files/15472d8a6e2fa66bc62b4249965df2fc.png?w=500&auto=format",
         "allTimeVolume": 0.3579,
         "floorAskPrice": {
            "currency": {
               "contract": "0x0000000000000000000000000000000000000000",
               "name": "Ether",
               "symbol": "ETH",
               "decimals": 18
            },
            "amount": {
               "raw": "29000000000000000",
               "decimal": 0.029,
               "usd": 54.16009,
               "native": 0.029
            }
         },
         "openseaVerificationStatus": "not_requested"
      },
      {
         "collectionId": "0x58ae0de454f76a1cf71cb3cb4dc7d1b3d655f86d",
         "name": "Sudo Bastard Miladys",
         "slug": "sudo-bastard-miladys",
         "contract": "0x58ae0de454f76a1cf71cb3cb4dc7d1b3d655f86d",
         "image": "https://i.seadn.io/gcs/files/331d756e5ee001ce8b6710e6d57ea7dc.jpg?w=500&auto=format",
         "allTimeVolume": 0.34152,
         "floorAskPrice": {
            "currency": {
               "contract": "0x0000000000000000000000000000000000000000",
               "name": "Ether",
               "symbol": "ETH",
               "decimals": 18
            },
            "amount": {
               "raw": "3839306472460760",
               "decimal": 0.00384,
               "usd": 7.17025,
               "native": 0.00384
            }
         },
         "openseaVerificationStatus": "not_requested"
      }
   ]
}
